setup.py
distributions_gaussian_binoomial/Binomialdistribution.py
distributions_gaussian_binoomial/Gaussiandistribution.py
distributions_gaussian_binoomial/Generaldistribution.py
distributions_gaussian_binoomial/__init__.py
distributions_gaussian_binoomial.egg-info/PKG-INFO
distributions_gaussian_binoomial.egg-info/SOURCES.txt
distributions_gaussian_binoomial.egg-info/dependency_links.txt
distributions_gaussian_binoomial.egg-info/not-zip-safe
distributions_gaussian_binoomial.egg-info/top_level.txt