Metadata-Version: 1.0
Name: distributions-gaussian-binoomial
Version: 0.12
Summary: Gaussian distributions and binoomial distributions
Home-page: UNKNOWN
Author: Venkteshwar Tripathi
Author-email: tripathivenkteshwar@gmail.com
License: UNKNOWN
Platform: UNKNOWN
